<?xml version="1.0" encoding="UTF-8" standalone="yes"?>
<sst xmlns="http://schemas.openxmlformats.org/spreadsheetml/2006/main" count="4" uniqueCount="2"><si><t>title</t></si><si><t>This page aims to collect all relevant information on projects that I am working on, whether that be through jobs, personal projects, or otherwise. Do feel free to contact me should you want to chat or know me further!

Below you can find my CV, my programming projects (ongoing, finished, or postponed), as well as other more personal projects.</t></si></sst>